rust_fatigue-0.1.7.dist-info/METADATA
rust_fatigue-0.1.7.dist-info/WHEEL
rustfatigue/__init__.py
rustfatigue/rustfatigue.cp313-win_amd64.pyd
rustfatigue/rustfatigue.pyi
rustfatigue/rustinterface.py
rustfatigue/tests/rustfatigue_test.py
rust_fatigue-0.1.7.dist-info/RECORD
