Metadata-Version: 2.4
Name: rust-fatigue
Version: 0.1.7
Requires-Dist: numpy>=1.21.6
Summary: A damage equivalent load calculator for Python written in Rust.
Author-email: Jaime Liew <jaimeliew1@gmail.com>
License: MIT
Requires-Python: >=3.8
Project-URL: Source Code, https://github.com/jaimeliew1/rustfatigue
